{"nodes": [{"id": "pkg_witness_qa", "label": "witness-qa", "file_type": "code", "type": "package", "ecosystem": "python", "source_file": "pyproject.toml", "source_location": "L1", "version": "1.2.0"}], "edges": [{"source": "pkg_witness_qa", "target": "pkg_appium_python_client", "relation": "depends_on", "context": "dependency", "confidence": "EXTRACTED", "confidence_score": 1.0, "source_file": "pyproject.toml", "source_location": "L1", "weight": 1.0}, {"source": "pkg_witness_qa", "target": "pkg_httpx", "relation": "depends_on", "context": "dependency", "confidence": "EXTRACTED", "confidence_score": 1.0, "source_file": "pyproject.toml", "source_location": "L1", "weight": 1.0}, {"source": "pkg_witness_qa", "target": "pkg_pexpect", "relation": "depends_on", "context": "dependency", "confidence": "EXTRACTED", "confidence_score": 1.0, "source_file": "pyproject.toml", "source_location": "L1", "weight": 1.0}, {"source": "pkg_witness_qa", "target": "pkg_pillow", "relation": "depends_on", "context": "dependency", "confidence": "EXTRACTED", "confidence_score": 1.0, "source_file": "pyproject.toml", "source_location": "L1", "weight": 1.0}, {"source": "pkg_witness_qa", "target": "pkg_playwright", "relation": "depends_on", "context": "dependency", "confidence": "EXTRACTED", "confidence_score": 1.0, "source_file": "pyproject.toml", "source_location": "L1", "weight": 1.0}, {"source": "pkg_witness_qa", "target": "pkg_pydantic", "relation": "depends_on", "context": "dependency", "confidence": "EXTRACTED", "confidence_score": 1.0, "source_file": "pyproject.toml", "source_location": "L1", "weight": 1.0}, {"source": "pkg_witness_qa", "target": "pkg_pyyaml", "relation": "depends_on", "context": "dependency", "confidence": "EXTRACTED", "confidence_score": 1.0, "source_file": "pyproject.toml", "source_location": "L1", "weight": 1.0}, {"source": "pkg_witness_qa", "target": "pkg_rich", "relation": "depends_on", "context": "dependency", "confidence": "EXTRACTED", "confidence_score": 1.0, "source_file": "pyproject.toml", "source_location": "L1", "weight": 1.0}, {"source": "pkg_witness_qa", "target": "pkg_typer", "relation": "depends_on", "context": "dependency", "confidence": "EXTRACTED", "confidence_score": 1.0, "source_file": "pyproject.toml", "source_location": "L1", "weight": 1.0}]}